
        {
            "@context":"http://iiif.io/api/presentation/2/context.json",
            "@id":"http://data.momu.be/melijn/annotations/T94_187/0013.json",
            "@type":"sc:AnnotationList",
            "resources":[
                
                    {
                        "@type":"oa:Annotation",
                        "motivation":"sc:painting",
                        "resource":
                        {
                            "@type":"cnt:ContentAsText",
                            "format":"text/plain",
                            
                    "chars":"ougge Cootss"
                        },
                        "on":"https://museumstichting.resourcespace.com:8443/iiif/11519/canvas/322#xywh=1026,434,631,199"
                        
                            ,
                            "within":
        					{
        						"@id": "https://data.momu.be/melijn/MelijnT94_187_manifest_compleet_annotaties.json",
        						"@type": "sc:Manifest"
        					}
                        
                    },
                    {
                        "@type":"oa:Annotation",
                        "motivation":"sc:painting",
                        "resource":
                        {
                            "@type":"cnt:ContentAsText",
                            "format":"text/plain",
                            
                    "chars":"3 Junu 1695"
                        },
                        "on":"https://museumstichting.resourcespace.com:8443/iiif/11519/canvas/322#xywh=2549,431,591,167"
                        
                            ,
                            "within":
        					{
        						"@id": "https://data.momu.be/melijn/MelijnT94_187_manifest_compleet_annotaties.json",
        						"@type": "sc:Manifest"
        					}
                        
                    },
                    {
                        "@type":"oa:Annotation",
                        "motivation":"sc:painting",
                        "resource":
                        {
                            "@type":"cnt:ContentAsText",
                            "format":"text/plain",
                            
                    "chars":"ue brieven van 29 & 31 past ontfangen & t pack N34"
                        },
                        "on":"https://museumstichting.resourcespace.com:8443/iiif/11519/canvas/322#xywh=1089,528,2161,187"
                        
                            ,
                            "within":
        					{
        						"@id": "https://data.momu.be/melijn/MelijnT94_187_manifest_compleet_annotaties.json",
        						"@type": "sc:Manifest"
        					}
                        
                    },
                    {
                        "@type":"oa:Annotation",
                        "motivation":"sc:painting",
                        "resource":
                        {
                            "@type":"cnt:ContentAsText",
                            "format":"text/plain",
                            
                    "chars":"gelieft in antwort deser done osten reken van miyne"
                        },
                        "on":"https://museumstichting.resourcespace.com:8443/iiif/11519/canvas/322#xywh=1017,697,2233,133"
                        
                            ,
                            "within":
        					{
        						"@id": "https://data.momu.be/melijn/MelijnT94_187_manifest_compleet_annotaties.json",
        						"@type": "sc:Manifest"
        					}
                        
                    },
                    {
                        "@type":"oa:Annotation",
                        "motivation":"sc:painting",
                        "resource":
                        {
                            "@type":"cnt:ContentAsText",
                            "format":"text/plain",
                            
                    "chars":"3 packen te seynden, alsoo mjne trecken anders met wel"
                        },
                        "on":"https://museumstichting.resourcespace.com:8443/iiif/11519/canvas/322#xywh=1032,785,2247,140"
                        
                            ,
                            "within":
        					{
        						"@id": "https://data.momu.be/melijn/MelijnT94_187_manifest_compleet_annotaties.json",
        						"@type": "sc:Manifest"
        					}
                        
                    },
                    {
                        "@type":"oa:Annotation",
                        "motivation":"sc:painting",
                        "resource":
                        {
                            "@type":"cnt:ContentAsText",
                            "format":"text/plain",
                            
                    "chars":"can balaneeren, waer mede ick nu besrgh ble"
                        },
                        "on":"https://museumstichting.resourcespace.com:8443/iiif/11519/canvas/322#xywh=1116,869,1935,188"
                        
                            ,
                            "within":
        					{
        						"@id": "https://data.momu.be/melijn/MelijnT94_187_manifest_compleet_annotaties.json",
        						"@type": "sc:Manifest"
        					}
                        
                    },
                    {
                        "@type":"oa:Annotation",
                        "motivation":"sc:painting",
                        "resource":
                        {
                            "@type":"cnt:ContentAsText",
                            "format":"text/plain",
                            
                    "chars":"Amst"
                        },
                        "on":"https://museumstichting.resourcespace.com:8443/iiif/11519/canvas/322#xywh=977,1013,314,151"
                        
                            ,
                            "within":
        					{
        						"@id": "https://data.momu.be/melijn/MelijnT94_187_manifest_compleet_annotaties.json",
        						"@type": "sc:Manifest"
        					}
                        
                    },
                    {
                        "@type":"oa:Annotation",
                        "motivation":"sc:painting",
                        "resource":
                        {
                            "@type":"cnt:ContentAsText",
                            "format":"text/plain",
                            
                    "chars":"3 lams"
                        },
                        "on":"https://museumstichting.resourcespace.com:8443/iiif/11519/canvas/322#xywh=2788,984,334,195"
                        
                            ,
                            "within":
        					{
        						"@id": "https://data.momu.be/melijn/MelijnT94_187_manifest_compleet_annotaties.json",
        						"@type": "sc:Manifest"
        					}
                        
                    },
                    {
                        "@type":"oa:Annotation",
                        "motivation":"sc:painting",
                        "resource":
                        {
                            "@type":"cnt:ContentAsText",
                            "format":"text/plain",
                            
                    "chars":"melis Lanssen & Evert Coman"
                        },
                        "on":"https://museumstichting.resourcespace.com:8443/iiif/11519/canvas/322#xywh=1012,1023,1251,218"
                        
                            ,
                            "within":
        					{
        						"@id": "https://data.momu.be/melijn/MelijnT94_187_manifest_compleet_annotaties.json",
        						"@type": "sc:Manifest"
        					}
                        
                    },
                    {
                        "@type":"oa:Annotation",
                        "motivation":"sc:painting",
                        "resource":
                        {
                            "@type":"cnt:ContentAsText",
                            "format":"text/plain",
                            
                    "chars":"in gevolge den ue van 27 pas seynde ingesloten de rekeninge van"
                        },
                        "on":"https://museumstichting.resourcespace.com:8443/iiif/11519/canvas/322#xywh=1167,1121,2257,178"
                        
                            ,
                            "within":
        					{
        						"@id": "https://data.momu.be/melijn/MelijnT94_187_manifest_compleet_annotaties.json",
        						"@type": "sc:Manifest"
        					}
                        
                    },
                    {
                        "@type":"oa:Annotation",
                        "motivation":"sc:painting",
                        "resource":
                        {
                            "@type":"cnt:ContentAsText",
                            "format":"text/plain",
                            
                    "chars":"vercooghte 18 pyelakens, waer van op ue cour ue goet compt a 219.5"
                        },
                        "on":"https://museumstichting.resourcespace.com:8443/iiif/11519/canvas/322#xywh=996,1226,2402,152"
                        
                            ,
                            "within":
        					{
        						"@id": "https://data.momu.be/melijn/MelijnT94_187_manifest_compleet_annotaties.json",
        						"@type": "sc:Manifest"
        					}
                        
                    },
                    {
                        "@type":"oa:Annotation",
                        "motivation":"sc:painting",
                        "resource":
                        {
                            "@type":"cnt:ContentAsText",
                            "format":"text/plain",
                            
                    "chars":"wisselg waer van ue gelieft ofte magh disponeren al hoewel peet"
                        },
                        "on":"https://museumstichting.resourcespace.com:8443/iiif/11519/canvas/322#xywh=998,1343,2410,153"
                        
                            ,
                            "within":
        					{
        						"@id": "https://data.momu.be/melijn/MelijnT94_187_manifest_compleet_annotaties.json",
        						"@type": "sc:Manifest"
        					}
                        
                    },
                    {
                        "@type":"oa:Annotation",
                        "motivation":"sc:painting",
                        "resource":
                        {
                            "@type":"cnt:ContentAsText",
                            "format":"text/plain",
                            
                    "chars":"van den Cruyce noch niet heeft betaelt maer mits hij een goet maen"
                        },
                        "on":"https://museumstichting.resourcespace.com:8443/iiif/11519/canvas/322#xywh=1011,1429,2411,161"
                        
                            ,
                            "within":
        					{
        						"@id": "https://data.momu.be/melijn/MelijnT94_187_manifest_compleet_annotaties.json",
        						"@type": "sc:Manifest"
        					}
                        
                    },
                    {
                        "@type":"oa:Annotation",
                        "motivation":"sc:painting",
                        "resource":
                        {
                            "@type":"cnt:ContentAsText",
                            "format":"text/plain",
                            
                    "chars":"11 twijfele niet ofte die betalinge sal volgen neghter blijft sulckx voor"
                        },
                        "on":"https://museumstichting.resourcespace.com:8443/iiif/11519/canvas/322#xywh=1044,1511,2345,212"
                        
                            ,
                            "within":
        					{
        						"@id": "https://data.momu.be/melijn/MelijnT94_187_manifest_compleet_annotaties.json",
        						"@type": "sc:Manifest"
        					}
                        
                    },
                    {
                        "@type":"oa:Annotation",
                        "motivation":"sc:painting",
                        "resource":
                        {
                            "@type":"cnt:ContentAsText",
                            "format":"text/plain",
                            
                    "chars":"ue reken, inde lotterije hebbe voor ue noch niets gegeven &"
                        },
                        "on":"https://museumstichting.resourcespace.com:8443/iiif/11519/canvas/322#xywh=1019,1635,2343,146"
                        
                            ,
                            "within":
        					{
        						"@id": "https://data.momu.be/melijn/MelijnT94_187_manifest_compleet_annotaties.json",
        						"@type": "sc:Manifest"
        					}
                        
                    },
                    {
                        "@type":"oa:Annotation",
                        "motivation":"sc:painting",
                        "resource":
                        {
                            "@type":"cnt:ContentAsText",
                            "format":"text/plain",
                            
                    "chars":"contramande wert sulckx ingehouden iedts anders tot ue dinst"
                        },
                        "on":"https://museumstichting.resourcespace.com:8443/iiif/11519/canvas/322#xywh=1025,1738,2215,158"
                        
                            ,
                            "within":
        					{
        						"@id": "https://data.momu.be/melijn/MelijnT94_187_manifest_compleet_annotaties.json",
        						"@type": "sc:Manifest"
        					}
                        
                    },
                    {
                        "@type":"oa:Annotation",
                        "motivation":"sc:painting",
                        "resource":
                        {
                            "@type":"cnt:ContentAsText",
                            "format":"text/plain",
                            
                    "chars":"gelieft te commanderen wenschende"
                        },
                        "on":"https://museumstichting.resourcespace.com:8443/iiif/11519/canvas/322#xywh=1030,1869,1435,188"
                        
                            ,
                            "within":
        					{
        						"@id": "https://data.momu.be/melijn/MelijnT94_187_manifest_compleet_annotaties.json",
        						"@type": "sc:Manifest"
        					}
                        
                    },
                    {
                        "@type":"oa:Annotation",
                        "motivation":"sc:painting",
                        "resource":
                        {
                            "@type":"cnt:ContentAsText",
                            "format":"text/plain",
                            
                    "chars":"5 Jusnn"
                        },
                        "on":"https://museumstichting.resourcespace.com:8443/iiif/11519/canvas/322#xywh=2688,1906,416,221"
                        
                            ,
                            "within":
        					{
        						"@id": "https://data.momu.be/melijn/MelijnT94_187_manifest_compleet_annotaties.json",
        						"@type": "sc:Manifest"
        					}
                        
                    },
                    {
                        "@type":"oa:Annotation",
                        "motivation":"sc:painting",
                        "resource":
                        {
                            "@type":"cnt:ContentAsText",
                            "format":"text/plain",
                            
                    "chars":"brugge de Coits"
                        },
                        "on":"https://museumstichting.resourcespace.com:8443/iiif/11519/canvas/322#xywh=958,1989,782,239"
                        
                            ,
                            "within":
        					{
        						"@id": "https://data.momu.be/melijn/MelijnT94_187_manifest_compleet_annotaties.json",
        						"@type": "sc:Manifest"
        					}
                        
                    },
                    {
                        "@type":"oa:Annotation",
                        "motivation":"sc:painting",
                        "resource":
                        {
                            "@type":"cnt:ContentAsText",
                            "format":"text/plain",
                            
                    "chars":"3 deser was aen ue mijnen laesten tsedert den ue"
                        },
                        "on":"https://museumstichting.resourcespace.com:8443/iiif/11519/canvas/322#xywh=1111,2129,1993,179"
                        
                            ,
                            "within":
        					{
        						"@id": "https://data.momu.be/melijn/MelijnT94_187_manifest_compleet_annotaties.json",
        						"@type": "sc:Manifest"
        					}
                        
                    },
                    {
                        "@type":"oa:Annotation",
                        "motivation":"sc:painting",
                        "resource":
                        {
                            "@type":"cnt:ContentAsText",
                            "format":"text/plain",
                            
                    "chars":"van eerst gisteren becommen te laet om het packin"
                        },
                        "on":"https://museumstichting.resourcespace.com:8443/iiif/11519/canvas/322#xywh=1028,2247,2256,151"
                        
                            ,
                            "within":
        					{
        						"@id": "https://data.momu.be/melijn/MelijnT94_187_manifest_compleet_annotaties.json",
        						"@type": "sc:Manifest"
        					}
                        
                    },
                    {
                        "@type":"oa:Annotation",
                        "motivation":"sc:painting",
                        "resource":
                        {
                            "@type":"cnt:ContentAsText",
                            "format":"text/plain",
                            
                    "chars":"hier te houden tselve is dan gisteren vertrocken onder een"
                        },
                        "on":"https://museumstichting.resourcespace.com:8443/iiif/11519/canvas/322#xywh=1024,2338,2219,161"
                        
                            ,
                            "within":
        					{
        						"@id": "https://data.momu.be/melijn/MelijnT94_187_manifest_compleet_annotaties.json",
        						"@type": "sc:Manifest"
        					}
                        
                    },
                    {
                        "@type":"oa:Annotation",
                        "motivation":"sc:painting",
                        "resource":
                        {
                            "@type":"cnt:ContentAsText",
                            "format":"text/plain",
                            
                    "chars":"particuliers passavant & alsoo desen brief ue canter"
                        },
                        "on":"https://museumstichting.resourcespace.com:8443/iiif/11519/canvas/322#xywh=1011,2430,2215,194"
                        
                            ,
                            "within":
        					{
        						"@id": "https://data.momu.be/melijn/MelijnT94_187_manifest_compleet_annotaties.json",
        						"@type": "sc:Manifest"
        					}
                        
                    },
                    {
                        "@type":"oa:Annotation",
                        "motivation":"sc:painting",
                        "resource":
                        {
                            "@type":"cnt:ContentAsText",
                            "format":"text/plain",
                            
                    "chars":"hant syn voor tarrivement van dobbelier sooken ue"
                        },
                        "on":"https://museumstichting.resourcespace.com:8443/iiif/11519/canvas/322#xywh=1033,2517,2116,164"
                        
                            ,
                            "within":
        					{
        						"@id": "https://data.momu.be/melijn/MelijnT94_187_manifest_compleet_annotaties.json",
        						"@type": "sc:Manifest"
        					}
                        
                    },
                    {
                        "@type":"oa:Annotation",
                        "motivation":"sc:painting",
                        "resource":
                        {
                            "@type":"cnt:ContentAsText",
                            "format":"text/plain",
                            
                    "chars":"daer ien oorsien & iedts tot ue dinst b"
                        },
                        "on":"https://museumstichting.resourcespace.com:8443/iiif/11519/canvas/322#xywh=1020,2645,1642,150"
                        
                            ,
                            "within":
        					{
        						"@id": "https://data.momu.be/melijn/MelijnT94_187_manifest_compleet_annotaties.json",
        						"@type": "sc:Manifest"
        					}
                        
                    },
                    {
                        "@type":"oa:Annotation",
                        "motivation":"sc:painting",
                        "resource":
                        {
                            "@type":"cnt:ContentAsText",
                            "format":"text/plain",
                            
                    "chars":"5d"
                        },
                        "on":"https://museumstichting.resourcespace.com:8443/iiif/11519/canvas/322#xywh=2713,2743,221,163"
                        
                            ,
                            "within":
        					{
        						"@id": "https://data.momu.be/melijn/MelijnT94_187_manifest_compleet_annotaties.json",
        						"@type": "sc:Manifest"
        					}
                        
                    },
                    {
                        "@type":"oa:Annotation",
                        "motivation":"sc:painting",
                        "resource":
                        {
                            "@type":"cnt:ContentAsText",
                            "format":"text/plain",
                            
                    "chars":"Brussel Rousseau"
                        },
                        "on":"https://museumstichting.resourcespace.com:8443/iiif/11519/canvas/322#xywh=962,2772,805,184"
                        
                            ,
                            "within":
        					{
        						"@id": "https://data.momu.be/melijn/MelijnT94_187_manifest_compleet_annotaties.json",
        						"@type": "sc:Manifest"
        					}
                        
                    },
                    {
                        "@type":"oa:Annotation",
                        "motivation":"sc:painting",
                        "resource":
                        {
                            "@type":"cnt:ContentAsText",
                            "format":"text/plain",
                            
                    "chars":"faute d'occasion pas respondu la vre du 20 passé de puis"
                        },
                        "on":"https://museumstichting.resourcespace.com:8443/iiif/11519/canvas/322#xywh=1044,2828,2203,228"
                        
                            ,
                            "within":
        					{
        						"@id": "https://data.momu.be/melijn/MelijnT94_187_manifest_compleet_annotaties.json",
        						"@type": "sc:Manifest"
        					}
                        
                    },
                    {
                        "@type":"oa:Annotation",
                        "motivation":"sc:painting",
                        "resource":
                        {
                            "@type":"cnt:ContentAsText",
                            "format":"text/plain",
                            
                    "chars":"lanne estant finie, ie vous souhait la novelle ame"
                        },
                        "on":"https://museumstichting.resourcespace.com:8443/iiif/11519/canvas/322#xywh=1047,2984,2171,147"
                        
                            ,
                            "within":
        					{
        						"@id": "https://data.momu.be/melijn/MelijnT94_187_manifest_compleet_annotaties.json",
        						"@type": "sc:Manifest"
        					}
                        
                    },
                    {
                        "@type":"oa:Annotation",
                        "motivation":"sc:painting",
                        "resource":
                        {
                            "@type":"cnt:ContentAsText",
                            "format":"text/plain",
                            
                    "chars":"bienhurene avec toutte fire famille & plusieurs survente"
                        },
                        "on":"https://museumstichting.resourcespace.com:8443/iiif/11519/canvas/322#xywh=1037,3065,2320,134"
                        
                            ,
                            "within":
        					{
        						"@id": "https://data.momu.be/melijn/MelijnT94_187_manifest_compleet_annotaties.json",
        						"@type": "sc:Manifest"
        					}
                        
                    },
                    {
                        "@type":"oa:Annotation",
                        "motivation":"sc:painting",
                        "resource":
                        {
                            "@type":"cnt:ContentAsText",
                            "format":"text/plain",
                            
                    "chars":"templies de tratte sorte de bened cy ioint ie vous enorye"
                        },
                        "on":"https://museumstichting.resourcespace.com:8443/iiif/11519/canvas/322#xywh=1015,3182,2217,122"
                        
                            ,
                            "within":
        					{
        						"@id": "https://data.momu.be/melijn/MelijnT94_187_manifest_compleet_annotaties.json",
        						"@type": "sc:Manifest"
        					}
                        
                    },
                    {
                        "@type":"oa:Annotation",
                        "motivation":"sc:painting",
                        "resource":
                        {
                            "@type":"cnt:ContentAsText",
                            "format":"text/plain",
                            
                    "chars":"vre compt court p la quelle vrs grace mes t redonerce"
                        },
                        "on":"https://museumstichting.resourcespace.com:8443/iiif/11519/canvas/322#xywh=1054,3252,2333,196"
                        
                            ,
                            "within":
        					{
        						"@id": "https://data.momu.be/melijn/MelijnT94_187_manifest_compleet_annotaties.json",
        						"@type": "sc:Manifest"
        					}
                        
                    },
                    {
                        "@type":"oa:Annotation",
                        "motivation":"sc:painting",
                        "resource":
                        {
                            "@type":"cnt:ContentAsText",
                            "format":"text/plain",
                            
                    "chars":"de reste £33:2:- p vous priant de lexaminer &"
                        },
                        "on":"https://museumstichting.resourcespace.com:8443/iiif/11519/canvas/322#xywh=1041,3339,2247,157"
                        
                            ,
                            "within":
        					{
        						"@id": "https://data.momu.be/melijn/MelijnT94_187_manifest_compleet_annotaties.json",
        						"@type": "sc:Manifest"
        					}
                        
                    },
                    {
                        "@type":"oa:Annotation",
                        "motivation":"sc:painting",
                        "resource":
                        {
                            "@type":"cnt:ContentAsText",
                            "format":"text/plain",
                            
                    "chars":"n'adviser si vous trouvez d'accord on quelqi erreur a vre"
                        },
                        "on":"https://museumstichting.resourcespace.com:8443/iiif/11519/canvas/322#xywh=1013,3430,2204,161"
                        
                            ,
                            "within":
        					{
        						"@id": "https://data.momu.be/melijn/MelijnT94_187_manifest_compleet_annotaties.json",
        						"@type": "sc:Manifest"
        					}
                        
                    },
                    {
                        "@type":"oa:Annotation",
                        "motivation":"sc:painting",
                        "resource":
                        {
                            "@type":"cnt:ContentAsText",
                            "format":"text/plain",
                            
                    "chars":"on ma preiudice pour rectifier a ladvenant pour sallancer"
                        },
                        "on":"https://museumstichting.resourcespace.com:8443/iiif/11519/canvas/322#xywh=1035,3527,2213,208"
                        
                            ,
                            "within":
        					{
        						"@id": "https://data.momu.be/melijn/MelijnT94_187_manifest_compleet_annotaties.json",
        						"@type": "sc:Manifest"
        					}
                        
                    },
                    {
                        "@type":"oa:Annotation",
                        "motivation":"sc:painting",
                        "resource":
                        {
                            "@type":"cnt:ContentAsText",
                            "format":"text/plain",
                            
                    "chars":"en suitte"
                        },
                        "on":"https://museumstichting.resourcespace.com:8443/iiif/11519/canvas/322#xywh=1052,3669,380,113"
                        
                            ,
                            "within":
        					{
        						"@id": "https://data.momu.be/melijn/MelijnT94_187_manifest_compleet_annotaties.json",
        						"@type": "sc:Manifest"
        					}
                        
                    },
                    {
                        "@type":"oa:Annotation",
                        "motivation":"sc:painting",
                        "resource":
                        {
                            "@type":"cnt:ContentAsText",
                            "format":"text/plain",
                            
                    "chars":"5d"
                        },
                        "on":"https://museumstichting.resourcespace.com:8443/iiif/11519/canvas/322#xywh=2827,3756,248,125"
                        
                            ,
                            "within":
        					{
        						"@id": "https://data.momu.be/melijn/MelijnT94_187_manifest_compleet_annotaties.json",
        						"@type": "sc:Manifest"
        					}
                        
                    },
                    {
                        "@type":"oa:Annotation",
                        "motivation":"sc:painting",
                        "resource":
                        {
                            "@type":"cnt:ContentAsText",
                            "format":"text/plain",
                            
                    "chars":"Mecheb. Cornelis van Aken"
                        },
                        "on":"https://museumstichting.resourcespace.com:8443/iiif/11519/canvas/322#xywh=921,3711,1200,250"
                        
                            ,
                            "within":
        					{
        						"@id": "https://data.momu.be/melijn/MelijnT94_187_manifest_compleet_annotaties.json",
        						"@type": "sc:Manifest"
        					}
                        
                    },
                    {
                        "@type":"oa:Annotation",
                        "motivation":"sc:painting",
                        "resource":
                        {
                            "@type":"cnt:ContentAsText",
                            "format":"text/plain",
                            
                    "chars":"d staelen aen hem gesonden vandepyen a 38 stuy"
                        },
                        "on":"https://museumstichting.resourcespace.com:8443/iiif/11519/canvas/322#xywh=1112,3822,2159,210"
                        
                            ,
                            "within":
        					{
        						"@id": "https://data.momu.be/melijn/MelijnT94_187_manifest_compleet_annotaties.json",
        						"@type": "sc:Manifest"
        					}
                        
                    },
                    {
                        "@type":"oa:Annotation",
                        "motivation":"sc:painting",
                        "resource":
                        {
                            "@type":"cnt:ContentAsText",
                            "format":"text/plain",
                            
                    "chars":"e an n de e he"
                        },
                        "on":"https://museumstichting.resourcespace.com:8443/iiif/11519/canvas/322#xywh=3868,291,711,177"
                        
                            ,
                            "within":
        					{
        						"@id": "https://data.momu.be/melijn/MelijnT94_187_manifest_compleet_annotaties.json",
        						"@type": "sc:Manifest"
        					}
                        
                    },
                    {
                        "@type":"oa:Annotation",
                        "motivation":"sc:painting",
                        "resource":
                        {
                            "@type":"cnt:ContentAsText",
                            "format":"text/plain",
                            
                    "chars":"don"
                        },
                        "on":"https://museumstichting.resourcespace.com:8443/iiif/11519/canvas/322#xywh=5291,313,375,281"
                        
                            ,
                            "within":
        					{
        						"@id": "https://data.momu.be/melijn/MelijnT94_187_manifest_compleet_annotaties.json",
        						"@type": "sc:Manifest"
        					}
                        
                    },
                    {
                        "@type":"oa:Annotation",
                        "motivation":"sc:painting",
                        "resource":
                        {
                            "@type":"cnt:ContentAsText",
                            "format":"text/plain",
                            
                    "chars":"Mechelen de weduwe betrane"
                        },
                        "on":"https://museumstichting.resourcespace.com:8443/iiif/11519/canvas/322#xywh=3507,443,1222,194"
                        
                            ,
                            "within":
        					{
        						"@id": "https://data.momu.be/melijn/MelijnT94_187_manifest_compleet_annotaties.json",
        						"@type": "sc:Manifest"
        					}
                        
                    },
                    {
                        "@type":"oa:Annotation",
                        "motivation":"sc:painting",
                        "resource":
                        {
                            "@type":"cnt:ContentAsText",
                            "format":"text/plain",
                            
                    "chars":"staelen gesonden vande frrsetten a 38st & geadviseert"
                        },
                        "on":"https://museumstichting.resourcespace.com:8443/iiif/11519/canvas/322#xywh=3602,515,2085,230"
                        
                            ,
                            "within":
        					{
        						"@id": "https://data.momu.be/melijn/MelijnT94_187_manifest_compleet_annotaties.json",
        						"@type": "sc:Manifest"
        					}
                        
                    },
                    {
                        "@type":"oa:Annotation",
                        "motivation":"sc:painting",
                        "resource":
                        {
                            "@type":"cnt:ContentAsText",
                            "format":"text/plain",
                            
                    "chars":"den ontfanck vande ƒ 200:- vanden bode ayou"
                        },
                        "on":"https://museumstichting.resourcespace.com:8443/iiif/11519/canvas/322#xywh=3501,642,1784,222"
                        
                            ,
                            "within":
        					{
        						"@id": "https://data.momu.be/melijn/MelijnT94_187_manifest_compleet_annotaties.json",
        						"@type": "sc:Manifest"
        					}
                        
                    },
                    {
                        "@type":"oa:Annotation",
                        "motivation":"sc:painting",
                        "resource":
                        {
                            "@type":"cnt:ContentAsText",
                            "format":"text/plain",
                            
                    "chars":"5 Jaian 95"
                        },
                        "on":"https://museumstichting.resourcespace.com:8443/iiif/11519/canvas/322#xywh=5153,774,528,164"
                        
                            ,
                            "within":
        					{
        						"@id": "https://data.momu.be/melijn/MelijnT94_187_manifest_compleet_annotaties.json",
        						"@type": "sc:Manifest"
        					}
                        
                    },
                    {
                        "@type":"oa:Annotation",
                        "motivation":"sc:painting",
                        "resource":
                        {
                            "@type":"cnt:ContentAsText",
                            "format":"text/plain",
                            
                    "chars":"Meggelen vanaken"
                        },
                        "on":"https://museumstichting.resourcespace.com:8443/iiif/11519/canvas/322#xywh=3405,822,1046,237"
                        
                            ,
                            "within":
        					{
        						"@id": "https://data.momu.be/melijn/MelijnT94_187_manifest_compleet_annotaties.json",
        						"@type": "sc:Manifest"
        					}
                        
                    },
                    {
                        "@type":"oa:Annotation",
                        "motivation":"sc:painting",
                        "resource":
                        {
                            "@type":"cnt:ContentAsText",
                            "format":"text/plain",
                            
                    "chars":"Monsieur ick hebbe u bret van 23 passato ontfangen"
                        },
                        "on":"https://museumstichting.resourcespace.com:8443/iiif/11519/canvas/322#xywh=3450,919,2258,237"
                        
                            ,
                            "within":
        					{
        						"@id": "https://data.momu.be/melijn/MelijnT94_187_manifest_compleet_annotaties.json",
        						"@type": "sc:Manifest"
        					}
                        
                    },
                    {
                        "@type":"oa:Annotation",
                        "motivation":"sc:painting",
                        "resource":
                        {
                            "@type":"cnt:ContentAsText",
                            "format":"text/plain",
                            
                    "chars":"diende de drjondert guldens wisselgeldens daer bij vermelt in gevolg"
                        },
                        "on":"https://museumstichting.resourcespace.com:8443/iiif/11519/canvas/322#xywh=3423,1027,2271,184"
                        
                            ,
                            "within":
        					{
        						"@id": "https://data.momu.be/melijn/MelijnT94_187_manifest_compleet_annotaties.json",
        						"@type": "sc:Manifest"
        					}
                        
                    },
                    {
                        "@type":"oa:Annotation",
                        "motivation":"sc:painting",
                        "resource":
                        {
                            "@type":"cnt:ContentAsText",
                            "format":"text/plain",
                            
                    "chars":"de quitantie aen den bode medegeven worden oock op u rekenie"
                        },
                        "on":"https://museumstichting.resourcespace.com:8443/iiif/11519/canvas/322#xywh=3428,1121,2272,175"
                        
                            ,
                            "within":
        					{
        						"@id": "https://data.momu.be/melijn/MelijnT94_187_manifest_compleet_annotaties.json",
        						"@type": "sc:Manifest"
        					}
                        
                    },
                    {
                        "@type":"oa:Annotation",
                        "motivation":"sc:painting",
                        "resource":
                        {
                            "@type":"cnt:ContentAsText",
                            "format":"text/plain",
                            
                    "chars":"trant hier medegaende vergoeyt, bij de selve blijt uwe mij so"
                        },
                        "on":"https://museumstichting.resourcespace.com:8443/iiif/11519/canvas/322#xywh=3460,1215,2245,196"
                        
                            ,
                            "within":
        					{
        						"@id": "https://data.momu.be/melijn/MelijnT94_187_manifest_compleet_annotaties.json",
        						"@type": "sc:Manifest"
        					}
                        
                    },
                    {
                        "@type":"oa:Annotation",
                        "motivation":"sc:painting",
                        "resource":
                        {
                            "@type":"cnt:ContentAsText",
                            "format":"text/plain",
                            
                    "chars":"£155: nege 19 schellingen 10 groten de w gelieft naetesien"
                        },
                        "on":"https://museumstichting.resourcespace.com:8443/iiif/11519/canvas/322#xywh=3559,1306,2139,203"
                        
                            ,
                            "within":
        					{
        						"@id": "https://data.momu.be/melijn/MelijnT94_187_manifest_compleet_annotaties.json",
        						"@type": "sc:Manifest"
        					}
                        
                    },
                    {
                        "@type":"oa:Annotation",
                        "motivation":"sc:painting",
                        "resource":
                        {
                            "@type":"cnt:ContentAsText",
                            "format":"text/plain",
                            
                    "chars":"ende het accort bevindende ver volges te notteren op ieder"
                        },
                        "on":"https://museumstichting.resourcespace.com:8443/iiif/11519/canvas/322#xywh=3567,1404,2159,144"
                        
                            ,
                            "within":
        					{
        						"@id": "https://data.momu.be/melijn/MelijnT94_187_manifest_compleet_annotaties.json",
        						"@type": "sc:Manifest"
        					}
                        
                    },
                    {
                        "@type":"oa:Annotation",
                        "motivation":"sc:painting",
                        "resource":
                        {
                            "@type":"cnt:ContentAsText",
                            "format":"text/plain",
                            
                    "chars":"partije van den debet i het rabat afgetrocken het swe"
                        },
                        "on":"https://museumstichting.resourcespace.com:8443/iiif/11519/canvas/322#xywh=3571,1505,2157,144"
                        
                            ,
                            "within":
        					{
        						"@id": "https://data.momu.be/melijn/MelijnT94_187_manifest_compleet_annotaties.json",
        						"@type": "sc:Manifest"
        					}
                        
                    },
                    {
                        "@type":"oa:Annotation",
                        "motivation":"sc:painting",
                        "resource":
                        {
                            "@type":"cnt:ContentAsText",
                            "format":"text/plain",
                            
                    "chars":"laken is een hollans ende omdat ick dat niet minder en kan"
                        },
                        "on":"https://museumstichting.resourcespace.com:8443/iiif/11519/canvas/322#xywh=3537,1577,2189,150"
                        
                            ,
                            "within":
        					{
        						"@id": "https://data.momu.be/melijn/MelijnT94_187_manifest_compleet_annotaties.json",
        						"@type": "sc:Manifest"
        					}
                        
                    },
                    {
                        "@type":"oa:Annotation",
                        "motivation":"sc:painting",
                        "resource":
                        {
                            "@type":"cnt:ContentAsText",
                            "format":"text/plain",
                            
                    "chars":"laten als ick het is heb gegeven soo motte ick dat wederon"
                        },
                        "on":"https://museumstichting.resourcespace.com:8443/iiif/11519/canvas/322#xywh=3552,1636,2203,160"
                        
                            ,
                            "within":
        					{
        						"@id": "https://data.momu.be/melijn/MelijnT94_187_manifest_compleet_annotaties.json",
        						"@type": "sc:Manifest"
        					}
                        
                    },
                    {
                        "@type":"oa:Annotation",
                        "motivation":"sc:painting",
                        "resource":
                        {
                            "@type":"cnt:ContentAsText",
                            "format":"text/plain",
                            
                    "chars":"verwachten ochte soo het icliden belief ick sal onse different"
                        },
                        "on":"https://museumstichting.resourcespace.com:8443/iiif/11519/canvas/322#xywh=3561,1738,2190,143"
                        
                            ,
                            "within":
        					{
        						"@id": "https://data.momu.be/melijn/MelijnT94_187_manifest_compleet_annotaties.json",
        						"@type": "sc:Manifest"
        					}
                        
                    },
                    {
                        "@type":"oa:Annotation",
                        "motivation":"sc:painting",
                        "resource":
                        {
                            "@type":"cnt:ContentAsText",
                            "format":"text/plain",
                            
                    "chars":"in consideratie nemen op de eerste partije goet die uliden sal"
                        },
                        "on":"https://museumstichting.resourcespace.com:8443/iiif/11519/canvas/322#xywh=3559,1830,2185,139"
                        
                            ,
                            "within":
        					{
        						"@id": "https://data.momu.be/melijn/MelijnT94_187_manifest_compleet_annotaties.json",
        						"@type": "sc:Manifest"
        					}
                        
                    },
                    {
                        "@type":"oa:Annotation",
                        "motivation":"sc:painting",
                        "resource":
                        {
                            "@type":"cnt:ContentAsText",
                            "format":"text/plain",
                            
                    "chars":"koopen vermits het alrede in mijn bocken is gesloten ick hebbe"
                        },
                        "on":"https://museumstichting.resourcespace.com:8443/iiif/11519/canvas/322#xywh=3576,1910,2170,121"
                        
                            ,
                            "within":
        					{
        						"@id": "https://data.momu.be/melijn/MelijnT94_187_manifest_compleet_annotaties.json",
        						"@type": "sc:Manifest"
        					}
                        
                    },
                    {
                        "@type":"oa:Annotation",
                        "motivation":"sc:painting",
                        "resource":
                        {
                            "@type":"cnt:ContentAsText",
                            "format":"text/plain",
                            
                    "chars":"eenigh vars goet becomen daer onder eenige frisetten de"
                        },
                        "on":"https://museumstichting.resourcespace.com:8443/iiif/11519/canvas/322#xywh=3569,1988,2191,122"
                        
                            ,
                            "within":
        					{
        						"@id": "https://data.momu.be/melijn/MelijnT94_187_manifest_compleet_annotaties.json",
        						"@type": "sc:Manifest"
        					}
                        
                    },
                    {
                        "@type":"oa:Annotation",
                        "motivation":"sc:painting",
                        "resource":
                        {
                            "@type":"cnt:ContentAsText",
                            "format":"text/plain",
                            
                    "chars":"oock aenstons verhoeht sijn beordelijck l van dese medege"
                        },
                        "on":"https://museumstichting.resourcespace.com:8443/iiif/11519/canvas/322#xywh=3555,2063,2194,125"
                        
                            ,
                            "within":
        					{
        						"@id": "https://data.momu.be/melijn/MelijnT94_187_manifest_compleet_annotaties.json",
        						"@type": "sc:Manifest"
        					}
                        
                    },
                    {
                        "@type":"oa:Annotation",
                        "motivation":"sc:painting",
                        "resource":
                        {
                            "@type":"cnt:ContentAsText",
                            "format":"text/plain",
                            
                    "chars":"de stalen soo ick den de selve ofte eenige daer van aensta"
                        },
                        "on":"https://museumstichting.resourcespace.com:8443/iiif/11519/canvas/322#xywh=3546,2175,2170,97"
                        
                            ,
                            "within":
        					{
        						"@id": "https://data.momu.be/melijn/MelijnT94_187_manifest_compleet_annotaties.json",
        						"@type": "sc:Manifest"
        					}
                        
                    },
                    {
                        "@type":"oa:Annotation",
                        "motivation":"sc:painting",
                        "resource":
                        {
                            "@type":"cnt:ContentAsText",
                            "format":"text/plain",
                            
                    "chars":"134 stuijvers corant geelt gelieft te commanderen al"
                        },
                        "on":"https://museumstichting.resourcespace.com:8443/iiif/11519/canvas/322#xywh=3559,2274,2188,120"
                        
                            ,
                            "within":
        					{
        						"@id": "https://data.momu.be/melijn/MelijnT94_187_manifest_compleet_annotaties.json",
        						"@type": "sc:Manifest"
        					}
                        
                    },
                    {
                        "@type":"oa:Annotation",
                        "motivation":"sc:painting",
                        "resource":
                        {
                            "@type":"cnt:ContentAsText",
                            "format":"text/plain",
                            
                    "chars":"ueden overkomt sal ick de tonne biene uijt der hant"
                        },
                        "on":"https://museumstichting.resourcespace.com:8443/iiif/11519/canvas/322#xywh=3568,2319,2111,133"
                        
                            ,
                            "within":
        					{
        						"@id": "https://data.momu.be/melijn/MelijnT94_187_manifest_compleet_annotaties.json",
        						"@type": "sc:Manifest"
        					}
                        
                    },
                    {
                        "@type":"oa:Annotation",
                        "motivation":"sc:painting",
                        "resource":
                        {
                            "@type":"cnt:ContentAsText",
                            "format":"text/plain",
                            
                    "chars":"betalen ens daer van geen rekeningh te houden wenschende"
                        },
                        "on":"https://museumstichting.resourcespace.com:8443/iiif/11519/canvas/322#xywh=3526,2431,2220,115"
                        
                            ,
                            "within":
        					{
        						"@id": "https://data.momu.be/melijn/MelijnT94_187_manifest_compleet_annotaties.json",
        						"@type": "sc:Manifest"
        					}
                        
                    },
                    {
                        "@type":"oa:Annotation",
                        "motivation":"sc:painting",
                        "resource":
                        {
                            "@type":"cnt:ContentAsText",
                            "format":"text/plain",
                            
                    "chars":"ilden alle voors"
                        },
                        "on":"https://museumstichting.resourcespace.com:8443/iiif/11519/canvas/322#xywh=3556,2500,704,158"
                        
                            ,
                            "within":
        					{
        						"@id": "https://data.momu.be/melijn/MelijnT94_187_manifest_compleet_annotaties.json",
        						"@type": "sc:Manifest"
        					}
                        
                    },
                    {
                        "@type":"oa:Annotation",
                        "motivation":"sc:painting",
                        "resource":
                        {
                            "@type":"cnt:ContentAsText",
                            "format":"text/plain",
                            
                    "chars":"6 panu"
                        },
                        "on":"https://museumstichting.resourcespace.com:8443/iiif/11519/canvas/322#xywh=5284,2552,454,187"
                        
                            ,
                            "within":
        					{
        						"@id": "https://data.momu.be/melijn/MelijnT94_187_manifest_compleet_annotaties.json",
        						"@type": "sc:Manifest"
        					}
                        
                    },
                    {
                        "@type":"oa:Annotation",
                        "motivation":"sc:painting",
                        "resource":
                        {
                            "@type":"cnt:ContentAsText",
                            "format":"text/plain",
                            
                    "chars":"londen kent"
                        },
                        "on":"https://museumstichting.resourcespace.com:8443/iiif/11519/canvas/322#xywh=3434,2606,628,173"
                        
                            ,
                            "within":
        					{
        						"@id": "https://data.momu.be/melijn/MelijnT94_187_manifest_compleet_annotaties.json",
        						"@type": "sc:Manifest"
        					}
                        
                    },
                    {
                        "@type":"oa:Annotation",
                        "motivation":"sc:painting",
                        "resource":
                        {
                            "@type":"cnt:ContentAsText",
                            "format":"text/plain",
                            
                    "chars":"sence my last of 23 past recd yours of 24 ditto"
                        },
                        "on":"https://museumstichting.resourcespace.com:8443/iiif/11519/canvas/322#xywh=3500,2646,2207,205"
                        
                            ,
                            "within":
        					{
        						"@id": "https://data.momu.be/melijn/MelijnT94_187_manifest_compleet_annotaties.json",
        						"@type": "sc:Manifest"
        					}
                        
                    },
                    {
                        "@type":"oa:Annotation",
                        "motivation":"sc:painting",
                        "resource":
                        {
                            "@type":"cnt:ContentAsText",
                            "format":"text/plain",
                            
                    "chars":"shall cexspect some remises for I could have remitted"
                        },
                        "on":"https://museumstichting.resourcespace.com:8443/iiif/11519/canvas/322#xywh=3485,2782,2235,185"
                        
                            ,
                            "within":
        					{
        						"@id": "https://data.momu.be/melijn/MelijnT94_187_manifest_compleet_annotaties.json",
        						"@type": "sc:Manifest"
        					}
                        
                    },
                    {
                        "@type":"oa:Annotation",
                        "motivation":"sc:painting",
                        "resource":
                        {
                            "@type":"cnt:ContentAsText",
                            "format":"text/plain",
                            
                    "chars":"you this day a 31:9 a 10 en the flannels I ordered to"
                        },
                        "on":"https://museumstichting.resourcespace.com:8443/iiif/11519/canvas/322#xywh=3505,2853,2259,218"
                        
                            ,
                            "within":
        					{
        						"@id": "https://data.momu.be/melijn/MelijnT94_187_manifest_compleet_annotaties.json",
        						"@type": "sc:Manifest"
        					}
                        
                    },
                    {
                        "@type":"oa:Annotation",
                        "motivation":"sc:painting",
                        "resource":
                        {
                            "@type":"cnt:ContentAsText",
                            "format":"text/plain",
                            
                    "chars":"is be added to the dyed to make a pack of 40 p viz"
                        },
                        "on":"https://museumstichting.resourcespace.com:8443/iiif/11519/canvas/322#xywh=3417,2983,2234,204"
                        
                            ,
                            "within":
        					{
        						"@id": "https://data.momu.be/melijn/MelijnT94_187_manifest_compleet_annotaties.json",
        						"@type": "sc:Manifest"
        					}
                        
                    },
                    {
                        "@type":"oa:Annotation",
                        "motivation":"sc:painting",
                        "resource":
                        {
                            "@type":"cnt:ContentAsText",
                            "format":"text/plain",
                            
                    "chars":"those of 16 a 17 p to be the most part yett & rather"
                        },
                        "on":"https://museumstichting.resourcespace.com:8443/iiif/11519/canvas/322#xywh=3507,3076,2221,198"
                        
                            ,
                            "within":
        					{
        						"@id": "https://data.momu.be/melijn/MelijnT94_187_manifest_compleet_annotaties.json",
        						"@type": "sc:Manifest"
        					}
                        
                    },
                    {
                        "@type":"oa:Annotation",
                        "motivation":"sc:painting",
                        "resource":
                        {
                            "@type":"cnt:ContentAsText",
                            "format":"text/plain",
                            
                    "chars":"of 28 pence butt not to exccede that prise except"
                        },
                        "on":"https://museumstichting.resourcespace.com:8443/iiif/11519/canvas/322#xywh=3522,3178,2245,241"
                        
                            ,
                            "within":
        					{
        						"@id": "https://data.momu.be/melijn/MelijnT94_187_manifest_compleet_annotaties.json",
        						"@type": "sc:Manifest"
        					}
                        
                    },
                    {
                        "@type":"oa:Annotation",
                        "motivation":"sc:painting",
                        "resource":
                        {
                            "@type":"cnt:ContentAsText",
                            "format":"text/plain",
                            
                    "chars":"the superfine as by my order of 16 past I have"
                        },
                        "on":"https://museumstichting.resourcespace.com:8443/iiif/11519/canvas/322#xywh=3519,3265,2241,212"
                        
                            ,
                            "within":
        					{
        						"@id": "https://data.momu.be/melijn/MelijnT94_187_manifest_compleet_annotaties.json",
        						"@type": "sc:Manifest"
        					}
                        
                    },
                    {
                        "@type":"oa:Annotation",
                        "motivation":"sc:painting",
                        "resource":
                        {
                            "@type":"cnt:ContentAsText",
                            "format":"text/plain",
                            
                    "chars":"the pack N54 butt the flannels prouve deaver"
                        },
                        "on":"https://museumstichting.resourcespace.com:8443/iiif/11519/canvas/322#xywh=3538,3413,2219,168"
                        
                            ,
                            "within":
        					{
        						"@id": "https://data.momu.be/melijn/MelijnT94_187_manifest_compleet_annotaties.json",
        						"@type": "sc:Manifest"
        					}
                        
                    },
                    {
                        "@type":"oa:Annotation",
                        "motivation":"sc:painting",
                        "resource":
                        {
                            "@type":"cnt:ContentAsText",
                            "format":"text/plain",
                            
                    "chars":"then what I had before there fore lett my intrest"
                        },
                        "on":"https://museumstichting.resourcespace.com:8443/iiif/11519/canvas/322#xywh=3541,3434,2248,277"
                        
                            ,
                            "within":
        					{
        						"@id": "https://data.momu.be/melijn/MelijnT94_187_manifest_compleet_annotaties.json",
        						"@type": "sc:Manifest"
        					}
                        
                    },
                    {
                        "@type":"oa:Annotation",
                        "motivation":"sc:painting",
                        "resource":
                        {
                            "@type":"cnt:ContentAsText",
                            "format":"text/plain",
                            
                    "chars":"be observed in this dead time of sale hopeinge you"
                        },
                        "on":"https://museumstichting.resourcespace.com:8443/iiif/11519/canvas/322#xywh=3503,3589,2288,177"
                        
                            ,
                            "within":
        					{
        						"@id": "https://data.momu.be/melijn/MelijnT94_187_manifest_compleet_annotaties.json",
        						"@type": "sc:Manifest"
        					}
                        
                    },
                    {
                        "@type":"oa:Annotation",
                        "motivation":"sc:painting",
                        "resource":
                        {
                            "@type":"cnt:ContentAsText",
                            "format":"text/plain",
                            
                    "chars":"shall make itt ny advrantage to buy now, when"
                        },
                        "on":"https://museumstichting.resourcespace.com:8443/iiif/11519/canvas/322#xywh=3499,3701,2203,197"
                        
                            ,
                            "within":
        					{
        						"@id": "https://data.momu.be/melijn/MelijnT94_187_manifest_compleet_annotaties.json",
        						"@type": "sc:Manifest"
        					}
                        
                    },
                    {
                        "@type":"oa:Annotation",
                        "motivation":"sc:painting",
                        "resource":
                        {
                            "@type":"cnt:ContentAsText",
                            "format":"text/plain",
                            
                    "chars":"you meet 5 pack whites EE yeallouw marcks"
                        },
                        "on":"https://museumstichting.resourcespace.com:8443/iiif/11519/canvas/322#xywh=3517,3807,2210,213"
                        
                            ,
                            "within":
        					{
        						"@id": "https://data.momu.be/melijn/MelijnT94_187_manifest_compleet_annotaties.json",
        						"@type": "sc:Manifest"
        					}
                        
                    },
                    {
                        "@type":"oa:Annotation",
                        "motivation":"sc:painting",
                        "resource":
                        {
                            "@type":"cnt:ContentAsText",
                            "format":"text/plain",
                            
                    "chars":"& pire good:, buy them, provided they have the"
                        },
                        "on":"https://museumstichting.resourcespace.com:8443/iiif/11519/canvas/322#xywh=3438,3898,2262,210"
                        
                            ,
                            "within":
        					{
        						"@id": "https://data.momu.be/melijn/MelijnT94_187_manifest_compleet_annotaties.json",
        						"@type": "sc:Manifest"
        					}
                        
                    },
                    {
                        "@type":"oa:Annotation",
                        "motivation":"sc:painting",
                        "resource":
                        {
                            "@type":"cnt:ContentAsText",
                            "format":"text/plain",
                            
                    "chars":"1conditions for white more expressed before, I am"
                        },
                        "on":"https://museumstichting.resourcespace.com:8443/iiif/11519/canvas/322#xywh=3424,4039,2367,139"
                        
                            ,
                            "within":
        					{
        						"@id": "https://data.momu.be/melijn/MelijnT94_187_manifest_compleet_annotaties.json",
        						"@type": "sc:Manifest"
        					}
                        
                    },
                    {
                        "@type":"oa:Annotation",
                        "motivation":"sc:painting",
                        "resource":
                        {
                            "@type":"cnt:ContentAsText",
                            "format":"text/plain",
                            
                    "chars":"had astand for aspan clothes because I doe"
                        },
                        "on":"https://museumstichting.resourcespace.com:8443/iiif/11519/canvas/322#xywh=3493,4125,2203,187"
                        
                            ,
                            "within":
        					{
        						"@id": "https://data.momu.be/melijn/MelijnT94_187_manifest_compleet_annotaties.json",
        						"@type": "sc:Manifest"
        					}
                        
                    },
                    {
                        "@type":"oa:Annotation",
                        "motivation":"sc:painting",
                        "resource":
                        {
                            "@type":"cnt:ContentAsText",
                            "format":"text/plain",
                            
                    "chars":"not knon, what to order, & finde net one"
                        },
                        "on":"https://museumstichting.resourcespace.com:8443/iiif/11519/canvas/322#xywh=3476,4245,2167,129"
                        
                            ,
                            "within":
        					{
        						"@id": "https://data.momu.be/melijn/MelijnT94_187_manifest_compleet_annotaties.json",
        						"@type": "sc:Manifest"
        					}
                        
                    }
            ]
        }
    